homeApp/__init__.py
homeApp/admin.py
homeApp/apps.py
homeApp/models.py
homeApp/tests.py
homeApp/views.py
homeApp/migrations/__init__.py
proteinRMSFProject/__init__.py
proteinRMSFProject/settings.py
proteinRMSFProject/urls.py
proteinRMSFProject/wsgi.py
sdu_tao_test-2.0.dist-info/METADATA
sdu_tao_test-2.0.dist-info/WHEEL
sdu_tao_test-2.0.dist-info/top_level.txt
sdu_tao_test-2.0.dist-info/RECORD
